{"articleEnglish":"Article 104 provides penalty for sitting and voting in Parliament before making oath or affirmation under Article 99, or when not qualified or disqualified.","articleId":"article-104","articleNo":"104","chapter":"अध्याय II","chapterEn":"Parliament","chapterHi":"संसद","createdAt":"2026-06-19T09:27:48.912Z","date":"18 June 2026","displayOrder":104,"examUsefulPoints":["Article 104 — Penalty for sitting and voting.","याद रखने वाला बिंदु: ₹500 per day penalty.","यह Article 99 और 102 से जुड़ा है।"],"explanationHi":"अनुच्छेद 104 संसद में गलत तरीके से बैठने या मतदान करने पर दंड से संबंधित है। सांसद बनने के बाद सदन में बैठने या वोट देने से पहले अनुच्छेद 99 के अनुसार शपथ लेना आवश्यक है। यदि कोई व्यक्ति शपथ के बिना, अयोग्य होते हुए या कानून द्वारा प्रतिबंधित होने के बावजूद वोट देता है, तो उस पर जुर्माना लगाया जा सकता है। परीक्षा में इस अनुच्छेद से 500 रुपये प्रतिदिन दंड वाला तथ्य पूछा जा सकता है।","faqs":[{"answer":"शपथ से पहले या अयोग्य होकर संसद में बैठने/मतदान करने का दंड।","question":"अनुच्छेद 104 में किसका दंड है?"},{"answer":"प्रत्येक दिन के लिए 500 रुपये तक।","question":"अनुच्छेद 104 में दंड कितना है?"}],"id":"article-104","keyPoints":["शपथ से पहले बैठने या मतदान करने पर दंड।","अयोग्य व्यक्ति द्वारा मतदान करने पर दंड।","दंड 500 रुपये प्रतिदिन तक हो सकता है।"],"part":"भाग V","shortSummaryHi":"यह अनुच्छेद ऐसे व्यक्ति पर दंड का प्रावधान करता है जो शपथ लेने से पहले या अयोग्य होने के बावजूद संसद में बैठता या मतदान करता है। यदि कोई व्यक्ति जानबूझकर ऐसी स्थिति में सदन की कार्यवाही में भाग लेता है, तो उस पर प्रत्येक दिन के लिए 500 रुपये का दंड लगाया जा सकता है। यह प्रावधान संसद की कार्यवाही की वैधता और सदस्यता की मर्यादा बनाए रखने के लिए बनाया गया है।","slug":"article-104-penalty-for-sitting-and-voting-before-making-oath-or-when-disqualified","status":"published","subChapterEn":"Disqualifications of Members","subChapterHi":"सदस्यों की अयोग्यता","titleEn":"Penalty for sitting and voting before making oath or affirmation under article 99 or when not qualified or when disqualified","titleHi":"शपथ से पहले या अयोग्य होने पर बैठने और मतदान करने का दंड","updatedAt":"2026-06-19T09:27:48.912Z"}